esios/__init__.py
esios/client.py
esios/indicators.py
esios/offer_indicators.py
esios/archives/__init__.py
esios/archives/preprocessing.py
python_esios-0.2.7.dist-info/licenses/LICENSE
python_esios-0.2.7.dist-info/METADATA
python_esios-0.2.7.dist-info/WHEEL
python_esios-0.2.7.dist-info/top_level.txt
python_esios-0.2.7.dist-info/RECORD
