Metadata-Version: 2.4
Name: python-esios
Version: 0.2.7
Summary: A Python wrapper for the ESIOS API
Home-page: https://github.com/datons/python-esios
Author: Jesús López
Author-email: jesus.lopez@datons.ai
Classifier: Programming Language :: Python :: 3
Classifier: License :: OSI Approved :: GNU General Public License v3 (GPLv3)
Classifier: Operating System :: OS Independent
Requires-Python: >=3.6
License-File: LICENSE
Requires-Dist: requests
Requires-Dist: pandas
Dynamic: author
Dynamic: author-email
Dynamic: classifier
Dynamic: description
Dynamic: description-content-type
Dynamic: home-page
Dynamic: license-file
Dynamic: requires-dist
Dynamic: requires-python
Dynamic: summary
